{
  "name": "Mable Larson",
  "age": 64,
  "address": {
    "street": "Arfu Glen",
    "city": "Jiitoiz",
    "state": "LA",
    "zip": "59917"
  },
  "contact": {
    "phone": "(241) 949-3386",
    "servicePhone": "800935755"
  },
  "birthday": "1963-09-10T16:35:36.828Z",
  "ip": "3.34.206.100",
  "foo": "bar",
  "profile": {
    "about": "Huded silabu rap wep duwmecig semmunut bimcet gotbeim tokji rikzubod woupujut ga dahguz gasruztas linpe muzahisu. Rewopiz uzetobar diepi jesha vansu obo pugciit vavepzi ci ufapocu da ucdaru awmev tebuh sikfec. Dircoros nuj rib ge sisasauw mibe cugcebe amozicu hun ci vi rewfaza. Zum dovsedpa ozuavji sozo jekahonu du padmurwoc hak ofa piv uniow celzoz.",
    "bio": "Favwu dusevat iszir vufdedifo huhwuhib mi onaka sizuzjen cuna wo ovso zakaf ho dapag gefemi bewlozzih setuf dor. Aceapisun mi kawi hamsuf anbizna af win lazpelwuv em vamaco ildufji fafze. Ofo limampew larki baf jithe pietu jew duzaf zibbigu idi fehuh weno pezof wuritoz. Cimipte wedcorho eferev azukecna lo ucame apa ufiata lawuniboz ratalaco mienrat sujuut viko vuw wokicu egza fud. Ad ipzoca jakdum lajalcoh vogzos nah camosi fiuvcel nib mer licdonvi padojiz seem obigu ec. Lor lo vec uze loggig te evupoke pivmono sakebba gukwo ra emhas evili. Wukjoj ighahid zujab giw ziow zakved nozmigi hapsaizo fipaf diva gipkimid gos pezfor inizon lectehet ozuwuluf tirha aleusi."
  },
  "apiKey": "833f1adca3bb28f78adb4eced558c92aeec415ddadd3da96329e9b50242a425c",
  "currency": {
    "code": "BDT",
    "name": "Bangladesh Taka"
  }
}