{
  "name": "Cory Hunt",
  "age": 63,
  "address": {
    "street": "Eleruk Key",
    "city": "Towkilako",
    "state": "MI",
    "zip": "57748"
  },
  "contact": {
    "phone": "(822) 314-7889",
    "servicePhone": "800661462"
  },
  "birthday": "2005-04-07T08:16:13.093Z",
  "ip": "39.89.175.189",
  "foo": "bar",
  "profile": {
    "about": "Bo zozfupvuh devucir lagjunbaz tucabopo dajalif ledumgav ekodev ra rac sore mucofib positwo. Buv mi zovazku wemseket mugew ijzegu izo odomo otniv tig waah ru ageefo bejmiv. Caza ubakjop afhopso pibujuda won wancikbo fe uk tutnedo zesam wedemup poajum suda fijmuj de hilunene. Muncoij madfono ukbeone esi keabipe uvahubep utuwaob wiap wi jobje cumuze tus tacze siwono soplo.",
    "bio": "Bi ta duvfih ubasa nurmaz za ev luhadmoc mednip ak to fotallu nirasag uhideccum. Napuvor nukgoj ridjij ni iwenivkun ho ci lano uljih vaf gistauz reahi nozofez. Wo juv idivuhe efuenho parnanveg vibgep fuvmuw leude abaeg mum ado ufeuhigo mivahvu oksi agapafzed vas buczoje. Wejow uj as wowgif erimo cuwo zunooh mildava rudsafob vefo tuw fobjiki. Ti var lus egudeza re irwegsoc ov po nolgevduh tejliso ulfutu gonumdek op ov rul fovi gulpego jeg."
  },
  "apiKey": "a6fd61fe8da4906c02016a73004f7c05257915385372215f98c1b208b7a70d38",
  "currency": {
    "code": "KHR",
    "name": "Cambodia Riel"
  }
}